snoopy_log_collator/Collator.py
snoopy_log_collator/Config.py
snoopy_log_collator/KeyedReader.py
snoopy_log_collator/KeyedReaderTree.py
snoopy_log_collator/Mapper.py
snoopy_log_collator/PostProcessor.py
snoopy_log_collator/Reader.py
snoopy_log_collator/Scanner.py
snoopy_log_collator/__init__.py
snoopy_log_collator/__main__.py
snoopy_log_collator/util.py
snoopy_log_collator/version.py
snoopy_log_collator-0.7.2.dist-info/LICENSE
snoopy_log_collator-0.7.2.dist-info/METADATA
snoopy_log_collator-0.7.2.dist-info/WHEEL
snoopy_log_collator-0.7.2.dist-info/entry_points.txt
snoopy_log_collator-0.7.2.dist-info/top_level.txt
snoopy_log_collator-0.7.2.dist-info/RECORD
